scraperapi_sdk/__init__.py
scraperapi_sdk/__version__.py
scraperapi_sdk/_client.py
scraperapi_sdk/exceptions.py
scraperapi_sdk-1.5.2.dist-info/METADATA
scraperapi_sdk-1.5.2.dist-info/WHEEL
scraperapi_sdk-1.5.2.dist-info/RECORD
