Metadata-Version: 2.1
Name: scraperapi-sdk
Version: 1.5.2
Summary: ScraperAPI Python SDK
Author: ScraperAPI
Requires-Python: >=3.8
Classifier: Programming Language :: Python :: 3
Classifier: Programming Language :: Python :: 3.8
Classifier: Programming Language :: Python :: 3.9
Classifier: Programming Language :: Python :: 3.10
Classifier: Programming Language :: Python :: 3.11
Classifier: Programming Language :: Python :: 3.12
Requires-Dist: requests (==2.31.0)
